[
    {
      "_id" : { "$oid" : "67a7e6b795029801ea9464c3" },
      "name" : "Veiculo",
      "usuario_id" : { "$oid" : "67a787eca76536c514c28bd0" }
    },
    {
      "_id" : { "$oid" : "67a7e81ad015b9560f2d6abe" },
      "name" : "casa",
      "usuario_id" : { "$oid" : "67a401922b5e20ce70a67cf0" }
    },
    {
      "_id" : { "$oid" : "67a7e820d015b9560f2d6abf" },
      "name" : "Veiculo",
      "usuario_id" : { "$oid" : "67a401922b5e20ce70a67cf0" }
    },
    {
      "_id" : { "$oid" : "67a8a912cbfcd9485bb937c9" },
      "name" : "Extra",
      "usuario_id" : { "$oid" : "67a401922b5e20ce70a67cf0" }
    },
    {
      "_id" : { "$oid" : "67a8a917cbfcd9485bb937ca" },
      "name" : "criancas",
      "usuario_id" : { "$oid" : "67a401922b5e20ce70a67cf0" }
    },
    {
      "_id" : { "$oid" : "67a8a91ecbfcd9485bb937cb" },
      "name" : "Aline",
      "usuario_id" : { "$oid" : "67a401922b5e20ce70a67cf0" }
    },
    {
      "_id" : { "$oid" : "67a8a934cbfcd9485bb937cc" },
      "name" : "Salario",
      "usuario_id" : { "$oid" : "67a401922b5e20ce70a67cf0" }
    },
    {
      "_id" : { "$oid" : "67a8ab73fdbae2565d16849b" },
      "name" : "so meu",
      "usuario_id" : { "$oid" : "67a787eca76536c514c28bd0" }
    },
    {
      "_id" : { "$oid" : "67ab52fbd365836e4dc89aa8" },
      "name" : "Manu",
      "usuario_id" : { "$oid" : "67a401922b5e20ce70a67cf0" }
    }
  ]
  